metastock2pd/__init__.py
metastock2pd/_metastock2pd.py
metastock2pd-1.0.2.dist-info/LICENSE
metastock2pd-1.0.2.dist-info/METADATA
metastock2pd-1.0.2.dist-info/WHEEL
metastock2pd-1.0.2.dist-info/top_level.txt
metastock2pd-1.0.2.dist-info/RECORD
