Metadata-Version: 2.1
Name: metastock2pd
Version: 1.0.2
Summary: Utilities for data manipulation including creation of DAGs and tables
Home-page: https://github.com/gityoav/metastock2pd
Author: Yoav Git
Author-email: yoav.git@gmail.com
Project-URL: Bug Tracker, https://github.com/gityoav/metastock2pd/issues
Classifier: Programming Language :: Python :: 3
Classifier: License :: OSI Approved :: MIT License
Classifier: Operating System :: OS Independent
Requires-Python: >=3.6
License-File: LICENSE
Requires-Dist: pandas
